junc_utils/__init__.py
junc_utils/annotate.py
junc_utils/associate.py
junc_utils/exonization_pair.py
junc_utils/logger.py
junc_utils/parser.py
junc_utils/run.py
junc_utils/utils.py
junc_utils/version.py
junc_utils-0.5.2.dist-info/LICENSE
junc_utils-0.5.2.dist-info/METADATA
junc_utils-0.5.2.dist-info/WHEEL
junc_utils-0.5.2.dist-info/entry_points.txt
junc_utils-0.5.2.dist-info/top_level.txt
junc_utils-0.5.2.dist-info/RECORD
